cp/__init__.py
cp/__main__.py
cptemplate-1.0.4.dist-info/LICENSE
cptemplate-1.0.4.dist-info/METADATA
cptemplate-1.0.4.dist-info/WHEEL
cptemplate-1.0.4.dist-info/entry_points.txt
cptemplate-1.0.4.dist-info/top_level.txt
cptemplate-1.0.4.dist-info/RECORD
