Metadata-Version: 2.1
Name: cptemplate
Version: 1.0.4
Summary: competitive programming template
Home-page: https://github.com/Devansh3712/cptemplate
Author: Devansh Singh
Author-email: devanshamity@gmail.com
License: MIT
Platform: UNKNOWN
Classifier: Programming Language :: Python :: 3
Classifier: License :: OSI Approved :: MIT License
Classifier: Operating System :: OS Independent
Requires-Dist: click (==7.1.2)
Requires-Dist: numpy (==1.19.4)
